bbrio_package_initial/__init__.py
bbrio_package_initial/chi_performance.py
bbrio_package_initial/chi_performance_parsed_table.py
chi_bhargab_2-0.0.4.dist-info/LICENSE.txt
chi_bhargab_2-0.0.4.dist-info/METADATA
chi_bhargab_2-0.0.4.dist-info/WHEEL
chi_bhargab_2-0.0.4.dist-info/top_level.txt
chi_bhargab_2-0.0.4.dist-info/RECORD
