Metadata-Version: 2.1
Name: chi-bhargab-2
Version: 0.0.4
Author: Bhargab Ganguli
Author-email: bhargab.ganguli@gmail.com
License: MIT
Classifier: Programming Language :: Python :: 3
Classifier: License :: OSI Approved :: MIT License
Classifier: Operating System :: OS Independent
License-File: LICENSE.txt
Requires-Dist: pandas
Requires-Dist: scipy.stats
Requires-Dist: math
